[
  {
    "name": "Colours",
    "settings": [
      {
        "type": "color",
        "label": "Primary Colour",
        "id": "color-primary"
      },
      {
        "type": "color",
        "label": "Secondary Colour",
        "id": "color-secondary"
      },
      {
        "type": "color",
        "label": "Text Colour",
        "id": "color-textBase"
      },
      {
        "type": "color",
        "label": "Heading Colour",
        "id": "color-textHeading"
      },
      {
        "type": "color",
        "label": "Border Colour",
        "id": "container-border-global-color-base"
      },
      {
        "type": "color",
        "label": "Page Background Colour",
        "id": "body-bg"
      },
      {
        "type": "color",
        "label": "Container Background Colour",
        "id": "container-fill-base"
      },
      {
        "type": "color",
        "label": "Header Background Colour",
        "id": "header-backgroundColor"
      },
      {
        "type": "color",
        "label": "Footer Background Colour",
        "id": "footer-backgroundColor"
      },
      {
        "type": "color",
        "label": "Footer Text Colour",
        "id": "footer-textColor"
      }
    ]
  },
  {
    "name": "Forms",
    "settings": [
      {
        "type": "heading",
        "content": "Input Fields"
      },
      {
        "type": "color",
        "label": "Field Background Colour",
        "id": "input-bg-color"
      },
      {
        "type": "color",
        "label": "Field Background Colour (Disabled)",
        "id": "input-disabled-bg"
      },
      {
        "type": "color",
        "label": "Field Border Colour",
        "id": "input-border-color"
      },
      {
        "type": "color",
        "label": "Field Border Colour (Active)",
        "id": "input-border-color-active"
      },
      {
        "type": "heading",
        "content": "Checkboxes & Radio Buttons"
      },
      {
        "type": "color",
        "label": "Button Icon Colour",
        "id": "checkRadio-color"
      },
      {
        "type": "color",
        "label": "Button Background Colour",
        "id": "checkRadio-backgroundColor"
      },
      {
        "type": "color",
        "label": "Button Border Colour",
        "id": "checkRadio-borderColor"
      }
    ]
  },
  {
    "name": "Page Features",
    "settings": [
      {
        "type": "heading",
        "content": "Enabled Features"
      },
      {
        "type": "checkbox",
        "label": "Enable Breadcrumbs",
        "force_reload": true,
        "id": "hide_breadcrumbs"
      },
      {
        "type": "checkbox",
        "label": "Enable Category Page Heading",
        "force_reload": true,
        "id": "hide_category_page_heading"
      },
      {
        "type": "checkbox",
        "label": "Enable Information Page Heading",
        "force_reload": true,
        "id": "hide_page_heading"
      },
      {
        "type": "checkbox",
        "label": "Enable Blog Page Heading",
        "force_reload": true,
        "id": "hide_blog_page_heading"
      },
      {
        "type": "checkbox",
        "label": "Enable Contact Page Heading",
        "force_reload": true,
        "id": "hide_contact_us_page_heading"
      },
      {
        "type": "heading",
        "content": "Image Loading"
      },
      {
        "type": "paragraph",
        "content": "Lazyloading allows for faster page loading speeds by loading images only when a user scrolls to them. Selecting the 'Lazyload' option will enable this feature fully. The 'Lazyload with LQIP' option will display a low-quality preview image and replace it with a high-quality image as the user scrolls. Finally, selecting 'Disabled' will turn this feature off entirely."
      },
      {
        "type": "select",
        "id": "lazyload_mode",
        "force_reload": true,
        "label": "Lazyloading Mode",
        "options": [
          {
            "value": "lazyload",
            "label": "Lazyload"
          },
          {
            "value": "lazyload+lqip",
            "label": "Lazyload with LQIP"
          },
          {
            "value": "disabled",
            "label": "Disabled"
          }
        ]
      }
    ]
  },
  {
    "name": "Page Messages",
    "settings": [
      {
        "type": "heading",
        "content": "Message Bar"
      },
      {
        "type": "checkbox",
        "label": "Enable Message Bar",
        "force_reload": true,
        "id": "hide_message_bar"
      },
      {
        "type": "color",
        "label": "Message Bar Background Colour",
        "id": "message-bar-backgroundColor"
      },
      {
        "type": "color",
        "label": "Message Bar Text Colour",
        "id": "message-bar-textColor"
      },
      {
        "type": "color",
        "label": "Message Bar Highlight Colour",
        "id": "message-bar-highlightColor"
      },
      {
        "type": "heading",
        "content": "Message Box"
      },
      {
        "type": "checkbox",
        "label": "Enable Message Box",
        "force_reload": true,
        "id": "hide_message_box"
      },
      {
        "type": "color",
        "label": "Message Box Background Colour",
        "id": "message-box-backgroundColor"
      },
      {
        "type": "color",
        "label": "Message Box Text Colour",
        "id": "message-box-textColor"
      },
      {
        "type": "color",
        "label": "Message Box Highlight Colour",
        "id": "message-box-highlightColor"
      }
    ]
  },
  {
    "name": "Homepage",
    "settings": [
      {
        "type": "heading",
        "content": "Carousel"
      },
      {
        "type": "checkbox",
        "label": "Enable Carousel Arrows",
        "force_reload": true,
        "id": "homepage_show_carousel_arrows"
      },
      {
        "type": "checkbox",
        "label": "Enable Carousel Indicators",
        "force_reload": true,
        "id": "homepage_show_carousel_indicators"
      }
    ]
  }
]
